{
  "@odata.context": "https://144.22.206.113:50000/b1s/v2/$metadata#ChartOfAccounts",
  "value": [
    {
      "Code": "1.3.02.01.003",
      "Name": "Máquinas e Equipamentos",
      "Balance": 12.560,
      "CashAccount": "tNO",
      "BudgetAccount": "tNO",
      "ActiveAccount": "tYES",
      "PrimaryAccount": "tNO",
      "AccountLevel": 5,
      "DataExportCode": null,
      "FatherAccountKey": "1.3.02.01",
      "ExternalCode": "130201003",
      "RateConversion": "tYES",
      "TaxLiableAccount": "tYES",
      "TaxExemptAccount": "tNO",
      "ExternalReconNo": null,
      "InternalReconNo": null,
      "AccountType": "at_Other",
      "AcctCurrency": "R$",
      "Balance_syscurr": 12.560,
      "Balance_FrgnCurr": 0.0,
      "Protected": "tNO",
      "ReconciledAccount": "tNO",
      "LiableForAdvances": "tNO",
      "ForeignName": null,
      "Details": null,
      "ProjectCode": null,
      "RevaluationCoordinated": "tNO",
      "LockManualTransaction": "tNO",
      "FormatCode": "1.3.02.01.003",
      "AllowChangeVatGroup": "tYES",
      "DefaultVatGroup": null,
      "Category": null,
      "TransactionCode": null,
      "LoadingType": "tNO",
      "LoadingFactorCode": null,
      "LoadingFactorCode2": null,
      "LoadingFactorCode3": null,
      "LoadingFactorCode4": null,
      "LoadingFactorCode5": null,
      "PlanningLevel": null,
      "DatevAccount": null,
      "DatevAutoAccount": "tNO",
      "DatevFirstDataEntry": "tYES",
      "AllowMultipleLinking": "tNO",
      "ProjectRelevant": "tNO",
      "DistributionRuleRelevant": "tNO",
      "DistributionRule2Relevant": "tNO",
      "DistributionRule3Relevant": "tNO",
      "DistributionRule4Relevant": "tNO",
      "DistributionRule5Relevant": "tNO",
      "BPLID": null,
      "BPLName": null,
      "VATRegNum": null,
      "AccountPurposeCode": null,
      "ReferentialAccountCode": null,
      "ValidFor": "tNO",
      "ValidFrom": null,
      "ValidTo": null,
      "ValidRemarks": null,
      "FrozenFor": "tNO",
      "FrozenFrom": null,
      "FrozenTo": null,
      "FrozenRemarks": null,
      "BlockManualPosting": "tYES",
      "CashFlowRelevant": "tNO",
      "PCN874ReportRelevant": "tNO",
      "PrimaryClosingAccount": null,
      "CostAccountingOnly": "tNO",
      "CostElementRelevant": "tNO",
      "CostElementCode": null,
      "StandardAccountCode": null,
      "TaxonomyCode": null,
      "IncomeClassificationCategory": null,
      "IncomeClassificationType": null,
      "ExpenseClassificationCategory": null,
      "ExpenseClassificationType": null,
      "U_TX_ContaCOSIF": null,
      "U_TX_CodigoDesIf": null,
      "U_TX_OutrosProdServDesIf": null,
      "U_TX_Des_Mista": null,
      "U_TX_Des_ContaSuperior": null,
      "U_TX_NatAccount": null,
      "U_TX_NAT_REC": null,
      "U_TX_TipoReceitaBruta": null,
      "U_TX_RegCaixa": null,
      "U_TX_OcultarConta": null,
      "U_K_PlanoECDECF": null,
      "U_K33PCusType": "-"
    },
    {
      "Code": "1.1.07",
      "Name": "OUTROS CRÉDITOS",
      "Balance": 0.0,
      "CashAccount": "tNO",
      "BudgetAccount": "tNO",
      "ActiveAccount": "tNO",
      "PrimaryAccount": "tNO",
      "AccountLevel": 3,
      "DataExportCode": null,
      "FatherAccountKey": "1.1",
      "ExternalCode": "1107",
      "RateConversion": "tYES",
      "TaxLiableAccount": "tYES",
      "TaxExemptAccount": "tNO",
      "ExternalReconNo": null,
      "InternalReconNo": null,
      "AccountType": "at_Other",
      "AcctCurrency": "R$",
      "Balance_syscurr": 0.0,
      "Balance_FrgnCurr": 0.0,
      "Protected": "tNO",
      "ReconciledAccount": "tNO",
      "LiableForAdvances": "tNO",
      "ForeignName": null,
      "Details": null,
      "ProjectCode": null,
      "RevaluationCoordinated": "tNO",
      "LockManualTransaction": "tNO",
      "FormatCode": "1.1.07",
      "AllowChangeVatGroup": "tYES",
      "DefaultVatGroup": null,
      "Category": null,
      "TransactionCode": null,
      "LoadingType": "tNO",
      "LoadingFactorCode": null,
      "LoadingFactorCode2": null,
      "LoadingFactorCode3": null,
      "LoadingFactorCode4": null,
      "LoadingFactorCode5": null,
      "PlanningLevel": null,
      "DatevAccount": null,
      "DatevAutoAccount": "tNO",
      "DatevFirstDataEntry": "tYES",
      "AllowMultipleLinking": "tNO",
      "ProjectRelevant": "tNO",
      "DistributionRuleRelevant": "tNO",
      "DistributionRule2Relevant": "tNO",
      "DistributionRule3Relevant": "tNO",
      "DistributionRule4Relevant": "tNO",
      "DistributionRule5Relevant": "tNO",
      "BPLID": null,
      "BPLName": null,
      "VATRegNum": null,
      "AccountPurposeCode": null,
      "ReferentialAccountCode": null,
      "ValidFor": "tNO",
      "ValidFrom": null,
      "ValidTo": null,
      "ValidRemarks": null,
      "FrozenFor": "tNO",
      "FrozenFrom": null,
      "FrozenTo": null,
      "FrozenRemarks": null,
      "BlockManualPosting": "tYES",
      "CashFlowRelevant": "tNO",
      "PCN874ReportRelevant": "tNO",
      "PrimaryClosingAccount": null,
      "CostAccountingOnly": "tNO",
      "CostElementRelevant": "tNO",
      "CostElementCode": null,
      "StandardAccountCode": null,
      "TaxonomyCode": null,
      "IncomeClassificationCategory": null,
      "IncomeClassificationType": null,
      "ExpenseClassificationCategory": null,
      "ExpenseClassificationType": null,
      "U_TX_ContaCOSIF": null,
      "U_TX_CodigoDesIf": null,
      "U_TX_OutrosProdServDesIf": null,
      "U_TX_Des_Mista": null,
      "U_TX_Des_ContaSuperior": null,
      "U_TX_NatAccount": null,
      "U_TX_NAT_REC": null,
      "U_TX_TipoReceitaBruta": null,
      "U_TX_RegCaixa": null,
      "U_TX_OcultarConta": null,
      "U_K_PlanoECDECF": null,
      "U_K33PCusType": "-"
    },
    {
      "Code": "1.1.01.03.001",
      "Name": "Banco Sicoob Coopecredi AG 3041-4 C/C 3128-3",
      "Balance": -497.330,
      "CashAccount": "tYES",
      "BudgetAccount": "tNO",
      "ActiveAccount": "tYES",
      "PrimaryAccount": "tNO",
      "AccountLevel": 5,
      "DataExportCode": null,
      "FatherAccountKey": "1.1.01.03",
      "ExternalCode": "110103001",
      "RateConversion": "tYES",
      "TaxLiableAccount": "tYES",
      "TaxExemptAccount": "tNO",
      "ExternalReconNo": null,
      "InternalReconNo": null,
      "AccountType": "at_Other",
      "AcctCurrency": "R$",
      "Balance_syscurr": -497.330,
      "Balance_FrgnCurr": 0.0,
      "Protected": "tNO",
      "ReconciledAccount": "tNO",
      "LiableForAdvances": "tNO",
      "ForeignName": null,
      "Details": null,
      "ProjectCode": null,
      "RevaluationCoordinated": "tNO",
      "LockManualTransaction": "tNO",
      "FormatCode": "1.1.01.03.001",
      "AllowChangeVatGroup": "tYES",
      "DefaultVatGroup": null,
      "Category": null,
      "TransactionCode": null,
      "LoadingType": "tNO",
      "LoadingFactorCode": null,
      "LoadingFactorCode2": null,
      "LoadingFactorCode3": null,
      "LoadingFactorCode4": null,
      "LoadingFactorCode5": null,
      "PlanningLevel": null,
      "DatevAccount": null,
      "DatevAutoAccount": "tNO",
      "DatevFirstDataEntry": "tYES",
      "AllowMultipleLinking": "tNO",
      "ProjectRelevant": "tNO",
      "DistributionRuleRelevant": "tNO",
      "DistributionRule2Relevant": "tNO",
      "DistributionRule3Relevant": "tNO",
      "DistributionRule4Relevant": "tNO",
      "DistributionRule5Relevant": "tNO",
      "BPLID": null,
      "BPLName": null,
      "VATRegNum": null,
      "AccountPurposeCode": null,
      "ReferentialAccountCode": null,
      "ValidFor": "tNO",
      "ValidFrom": null,
      "ValidTo": null,
      "ValidRemarks": null,
      "FrozenFor": "tNO",
      "FrozenFrom": null,
      "FrozenTo": null,
      "FrozenRemarks": null,
      "BlockManualPosting": "tNO",
      "CashFlowRelevant": "tYES",
      "PCN874ReportRelevant": "tNO",
      "PrimaryClosingAccount": null,
      "CostAccountingOnly": "tNO",
      "CostElementRelevant": "tNO",
      "CostElementCode": null,
      "StandardAccountCode": null,
      "TaxonomyCode": null,
      "IncomeClassificationCategory": null,
      "IncomeClassificationType": null,
      "ExpenseClassificationCategory": null,
      "ExpenseClassificationType": null,
      "U_TX_ContaCOSIF": null,
      "U_TX_CodigoDesIf": null,
      "U_TX_OutrosProdServDesIf": null,
      "U_TX_Des_Mista": null,
      "U_TX_Des_ContaSuperior": null,
      "U_TX_NatAccount": null,
      "U_TX_NAT_REC": null,
      "U_TX_TipoReceitaBruta": null,
      "U_TX_RegCaixa": null,
      "U_TX_OcultarConta": null,
      "U_K_PlanoECDECF": null,
      "U_K33PCusType": "-"
    },
    {
      "Code": "1.1.07.01",
      "Name": "ADIANTAMENTOS SALARIAIS",
      "Balance": 0.0,
      "CashAccount": "tNO",
      "BudgetAccount": "tNO",
      "ActiveAccount": "tNO",
      "PrimaryAccount": "tNO",
      "AccountLevel": 4,
      "DataExportCode": null,
      "FatherAccountKey": "1.1.07",
      "ExternalCode": "110701",
      "RateConversion": "tYES",
      "TaxLiableAccount": "tYES",
      "TaxExemptAccount": "tNO",
      "ExternalReconNo": null,
      "InternalReconNo": null,
      "AccountType": "at_Other",
      "AcctCurrency": "R$",
      "Balance_syscurr": 0.0,
      "Balance_FrgnCurr": 0.0,
      "Protected": "tNO",
      "ReconciledAccount": "tNO",
      "LiableForAdvances": "tNO",
      "ForeignName": null,
      "Details": null,
      "ProjectCode": null,
      "RevaluationCoordinated": "tNO",
      "LockManualTransaction": "tNO",
      "FormatCode": "1.1.07.01",
      "AllowChangeVatGroup": "tYES",
      "DefaultVatGroup": null,
      "Category": null,
      "TransactionCode": null,
      "LoadingType": "tNO",
      "LoadingFactorCode": null,
      "LoadingFactorCode2": null,
      "LoadingFactorCode3": null,
      "LoadingFactorCode4": null,
      "LoadingFactorCode5": null,
      "PlanningLevel": null,
      "DatevAccount": null,
      "DatevAutoAccount": "tNO",
      "DatevFirstDataEntry": "tYES",
      "AllowMultipleLinking": "tNO",
      "ProjectRelevant": "tNO",
      "DistributionRuleRelevant": "tNO",
      "DistributionRule2Relevant": "tNO",
      "DistributionRule3Relevant": "tNO",
      "DistributionRule4Relevant": "tNO",
      "DistributionRule5Relevant": "tNO",
      "BPLID": null,
      "BPLName": null,
      "VATRegNum": null,
      "AccountPurposeCode": null,
      "ReferentialAccountCode": null,
      "ValidFor": "tNO",
      "ValidFrom": null,
      "ValidTo": null,
      "ValidRemarks": null,
      "FrozenFor": "tNO",
      "FrozenFrom": null,
      "FrozenTo": null,
      "FrozenRemarks": null,
      "BlockManualPosting": "tYES",
      "CashFlowRelevant": "tNO",
      "PCN874ReportRelevant": "tNO",
      "PrimaryClosingAccount": null,
      "CostAccountingOnly": "tNO",
      "CostElementRelevant": "tNO",
      "CostElementCode": null,
      "StandardAccountCode": null,
      "TaxonomyCode": null,
      "IncomeClassificationCategory": null,
      "IncomeClassificationType": null,
      "ExpenseClassificationCategory": null,
      "ExpenseClassificationType": null,
      "U_TX_ContaCOSIF": null,
      "U_TX_CodigoDesIf": null,
      "U_TX_OutrosProdServDesIf": null,
      "U_TX_Des_Mista": null,
      "U_TX_Des_ContaSuperior": null,
      "U_TX_NatAccount": null,
      "U_TX_NAT_REC": null,
      "U_TX_TipoReceitaBruta": null,
      "U_TX_RegCaixa": null,
      "U_TX_OcultarConta": null,
      "U_K_PlanoECDECF": null,
      "U_K33PCusType": "-"
    },
    {
      "Code": "1.1.07.01.001",
      "Name": "Adiantamentos de Salário",
      "Balance": 0.0,
      "CashAccount": "tNO",
      "BudgetAccount": "tNO",
      "ActiveAccount": "tYES",
      "PrimaryAccount": "tNO",
      "AccountLevel": 5,
      "DataExportCode": null,
      "FatherAccountKey": "1.1.07.01",
      "ExternalCode": "110701001",
      "RateConversion": "tYES",
      "TaxLiableAccount": "tYES",
      "TaxExemptAccount": "tNO",
      "ExternalReconNo": null,
      "InternalReconNo": null,
      "AccountType": "at_Other",
      "AcctCurrency": "R$",
      "Balance_syscurr": 0.0,
      "Balance_FrgnCurr": 0.0,
      "Protected": "tNO",
      "ReconciledAccount": "tNO",
      "LiableForAdvances": "tNO",
      "ForeignName": null,
      "Details": null,
      "ProjectCode": null,
      "RevaluationCoordinated": "tNO",
      "LockManualTransaction": "tNO",
      "FormatCode": "1.1.07.01.001",
      "AllowChangeVatGroup": "tYES",
      "DefaultVatGroup": null,
      "Category": null,
      "TransactionCode": null,
      "LoadingType": "tNO",
      "LoadingFactorCode": null,
      "LoadingFactorCode2": null,
      "LoadingFactorCode3": null,
      "LoadingFactorCode4": null,
      "LoadingFactorCode5": null,
      "PlanningLevel": null,
      "DatevAccount": null,
      "DatevAutoAccount": "tNO",
      "DatevFirstDataEntry": "tYES",
      "AllowMultipleLinking": "tNO",
      "ProjectRelevant": "tNO",
      "DistributionRuleRelevant": "tNO",
      "DistributionRule2Relevant": "tNO",
      "DistributionRule3Relevant": "tNO",
      "DistributionRule4Relevant": "tNO",
      "DistributionRule5Relevant": "tNO",
      "BPLID": null,
      "BPLName": null,
      "VATRegNum": null,
      "AccountPurposeCode": null,
      "ReferentialAccountCode": null,
      "ValidFor": "tNO",
      "ValidFrom": null,
      "ValidTo": null,
      "ValidRemarks": null,
      "FrozenFor": "tNO",
      "FrozenFrom": null,
      "FrozenTo": null,
      "FrozenRemarks": null,
      "BlockManualPosting": "tNO",
      "CashFlowRelevant": "tNO",
      "PCN874ReportRelevant": "tNO",
      "PrimaryClosingAccount": null,
      "CostAccountingOnly": "tNO",
      "CostElementRelevant": "tNO",
      "CostElementCode": null,
      "StandardAccountCode": null,
      "TaxonomyCode": null,
      "IncomeClassificationCategory": null,
      "IncomeClassificationType": null,
      "ExpenseClassificationCategory": null,
      "ExpenseClassificationType": null,
      "U_TX_ContaCOSIF": null,
      "U_TX_CodigoDesIf": null,
      "U_TX_OutrosProdServDesIf": null,
      "U_TX_Des_Mista": null,
      "U_TX_Des_ContaSuperior": null,
      "U_TX_NatAccount": null,
      "U_TX_NAT_REC": null,
      "U_TX_TipoReceitaBruta": null,
      "U_TX_RegCaixa": null,
      "U_TX_OcultarConta": null,
      "U_K_PlanoECDECF": null,
      "U_K33PCusType": "-"
    },
    {
      "Code": "1.1.07.01.002",
      "Name": "Adiantamentos de Férias",
      "Balance": 0.0,
      "CashAccount": "tNO",
      "BudgetAccount": "tNO",
      "ActiveAccount": "tYES",
      "PrimaryAccount": "tNO",
      "AccountLevel": 5,
      "DataExportCode": null,
      "FatherAccountKey": "1.1.07.01",
      "ExternalCode": "110701002",
      "RateConversion": "tYES",
      "TaxLiableAccount": "tYES",
      "TaxExemptAccount": "tNO",
      "ExternalReconNo": null,
      "InternalReconNo": null,
      "AccountType": "at_Other",
      "AcctCurrency": "R$",
      "Balance_syscurr": 0.0,
      "Balance_FrgnCurr": 0.0,
      "Protected": "tNO",
      "ReconciledAccount": "tNO",
      "LiableForAdvances": "tNO",
      "ForeignName": null,
      "Details": null,
      "ProjectCode": null,
      "RevaluationCoordinated": "tNO",
      "LockManualTransaction": "tNO",
      "FormatCode": "1.1.07.01.002",
      "AllowChangeVatGroup": "tYES",
      "DefaultVatGroup": null,
      "Category": null,
      "TransactionCode": null,
      "LoadingType": "tNO",
      "LoadingFactorCode": null,
      "LoadingFactorCode2": null,
      "LoadingFactorCode3": null,
      "LoadingFactorCode4": null,
      "LoadingFactorCode5": null,
      "PlanningLevel": null,
      "DatevAccount": null,
      "DatevAutoAccount": "tNO",
      "DatevFirstDataEntry": "tYES",
      "AllowMultipleLinking": "tNO",
      "ProjectRelevant": "tNO",
      "DistributionRuleRelevant": "tNO",
      "DistributionRule2Relevant": "tNO",
      "DistributionRule3Relevant": "tNO",
      "DistributionRule4Relevant": "tNO",
      "DistributionRule5Relevant": "tNO",
      "BPLID": null,
      "BPLName": null,
      "VATRegNum": null,
      "AccountPurposeCode": null,
      "ReferentialAccountCode": null,
      "ValidFor": "tNO",
      "ValidFrom": null,
      "ValidTo": null,
      "ValidRemarks": null,
      "FrozenFor": "tNO",
      "FrozenFrom": null,
      "FrozenTo": null,
      "FrozenRemarks": null,
      "BlockManualPosting": "tNO",
      "CashFlowRelevant": "tNO",
      "PCN874ReportRelevant": "tNO",
      "PrimaryClosingAccount": null,
      "CostAccountingOnly": "tNO",
      "CostElementRelevant": "tNO",
      "CostElementCode": null,
      "StandardAccountCode": null,
      "TaxonomyCode": null,
      "IncomeClassificationCategory": null,
      "IncomeClassificationType": null,
      "ExpenseClassificationCategory": null,
      "ExpenseClassificationType": null,
      "U_TX_ContaCOSIF": null,
      "U_TX_CodigoDesIf": null,
      "U_TX_OutrosProdServDesIf": null,
      "U_TX_Des_Mista": null,
      "U_TX_Des_ContaSuperior": null,
      "U_TX_NatAccount": null,
      "U_TX_NAT_REC": null,
      "U_TX_TipoReceitaBruta": null,
      "U_TX_RegCaixa": null,
      "U_TX_OcultarConta": null,
      "U_K_PlanoECDECF": null,
      "U_K33PCusType": "-"
    },
    {
      "Code": "1.1.07.01.003",
      "Name": "Adiantamentos 13º Salário",
      "Balance": 0.0,
      "CashAccount": "tNO",
      "BudgetAccount": "tNO",
      "ActiveAccount": "tYES",
      "PrimaryAccount": "tNO",
      "AccountLevel": 5,
      "DataExportCode": null,
      "FatherAccountKey": "1.1.07.01",
      "ExternalCode": "110701003",
      "RateConversion": "tYES",
      "TaxLiableAccount": "tYES",
      "TaxExemptAccount": "tNO",
      "ExternalReconNo": null,
      "InternalReconNo": null,
      "AccountType": "at_Other",
      "AcctCurrency": "R$",
      "Balance_syscurr": 0.0,
      "Balance_FrgnCurr": 0.0,
      "Protected": "tNO",
      "ReconciledAccount": "tNO",
      "LiableForAdvances": "tNO",
      "ForeignName": null,
      "Details": null,
      "ProjectCode": null,
      "RevaluationCoordinated": "tNO",
      "LockManualTransaction": "tNO",
      "FormatCode": "1.1.07.01.003",
      "AllowChangeVatGroup": "tYES",
      "DefaultVatGroup": null,
      "Category": null,
      "TransactionCode": null,
      "LoadingType": "tNO",
      "LoadingFactorCode": null,
      "LoadingFactorCode2": null,
      "LoadingFactorCode3": null,
      "LoadingFactorCode4": null,
      "LoadingFactorCode5": null,
      "PlanningLevel": null,
      "DatevAccount": null,
      "DatevAutoAccount": "tNO",
      "DatevFirstDataEntry": "tYES",
      "AllowMultipleLinking": "tNO",
      "ProjectRelevant": "tNO",
      "DistributionRuleRelevant": "tNO",
      "DistributionRule2Relevant": "tNO",
      "DistributionRule3Relevant": "tNO",
      "DistributionRule4Relevant": "tNO",
      "DistributionRule5Relevant": "tNO",
      "BPLID": null,
      "BPLName": null,
      "VATRegNum": null,
      "AccountPurposeCode": null,
      "ReferentialAccountCode": null,
      "ValidFor": "tNO",
      "ValidFrom": null,
      "ValidTo": null,
      "ValidRemarks": null,
      "FrozenFor": "tNO",
      "FrozenFrom": null,
      "FrozenTo": null,
      "FrozenRemarks": null,
      "BlockManualPosting": "tNO",
      "CashFlowRelevant": "tNO",
      "PCN874ReportRelevant": "tNO",
      "PrimaryClosingAccount": null,
      "CostAccountingOnly": "tNO",
      "CostElementRelevant": "tNO",
      "CostElementCode": null,
      "StandardAccountCode": null,
      "TaxonomyCode": null,
      "IncomeClassificationCategory": null,
      "IncomeClassificationType": null,
      "ExpenseClassificationCategory": null,
      "ExpenseClassificationType": null,
      "U_TX_ContaCOSIF": null,
      "U_TX_CodigoDesIf": null,
      "U_TX_OutrosProdServDesIf": null,
      "U_TX_Des_Mista": null,
      "U_TX_Des_ContaSuperior": null,
      "U_TX_NatAccount": null,
      "U_TX_NAT_REC": null,
      "U_TX_TipoReceitaBruta": null,
      "U_TX_RegCaixa": null,
      "U_TX_OcultarConta": null,
      "U_K_PlanoECDECF": null,
      "U_K33PCusType": "-"
    },
    {
      "Code": "1.1.07.01.004",
      "Name": "Adiantamentos Pensão",
      "Balance": 0.0,
      "CashAccount": "tNO",
      "BudgetAccount": "tNO",
      "ActiveAccount": "tYES",
      "PrimaryAccount": "tNO",
      "AccountLevel": 5,
      "DataExportCode": null,
      "FatherAccountKey": "1.1.07.01",
      "ExternalCode": "110701004",
      "RateConversion": "tYES",
      "TaxLiableAccount": "tYES",
      "TaxExemptAccount": "tNO",
      "ExternalReconNo": null,
      "InternalReconNo": null,
      "AccountType": "at_Other",
      "AcctCurrency": "R$",
      "Balance_syscurr": 0.0,
      "Balance_FrgnCurr": 0.0,
      "Protected": "tNO",
      "ReconciledAccount": "tNO",
      "LiableForAdvances": "tNO",
      "ForeignName": null,
      "Details": null,
      "ProjectCode": null,
      "RevaluationCoordinated": "tNO",
      "LockManualTransaction": "tNO",
      "FormatCode": "1.1.07.01.004",
      "AllowChangeVatGroup": "tYES",
      "DefaultVatGroup": null,
      "Category": null,
      "TransactionCode": null,
      "LoadingType": "tNO",
      "LoadingFactorCode": null,
      "LoadingFactorCode2": null,
      "LoadingFactorCode3": null,
      "LoadingFactorCode4": null,
      "LoadingFactorCode5": null,
      "PlanningLevel": null,
      "DatevAccount": null,
      "DatevAutoAccount": "tNO",
      "DatevFirstDataEntry": "tYES",
      "AllowMultipleLinking": "tNO",
      "ProjectRelevant": "tNO",
      "DistributionRuleRelevant": "tNO",
      "DistributionRule2Relevant": "tNO",
      "DistributionRule3Relevant": "tNO",
      "DistributionRule4Relevant": "tNO",
      "DistributionRule5Relevant": "tNO",
      "BPLID": null,
      "BPLName": null,
      "VATRegNum": null,
      "AccountPurposeCode": null,
      "ReferentialAccountCode": null,
      "ValidFor": "tNO",
      "ValidFrom": null,
      "ValidTo": null,
      "ValidRemarks": null,
      "FrozenFor": "tNO",
      "FrozenFrom": null,
      "FrozenTo": null,
      "FrozenRemarks": null,
      "BlockManualPosting": "tNO",
      "CashFlowRelevant": "tNO",
      "PCN874ReportRelevant": "tNO",
      "PrimaryClosingAccount": null,
      "CostAccountingOnly": "tNO",
      "CostElementRelevant": "tNO",
      "CostElementCode": null,
      "StandardAccountCode": null,
      "TaxonomyCode": null,
      "IncomeClassificationCategory": null,
      "IncomeClassificationType": null,
      "ExpenseClassificationCategory": null,
      "ExpenseClassificationType": null,
      "U_TX_ContaCOSIF": null,
      "U_TX_CodigoDesIf": null,
      "U_TX_OutrosProdServDesIf": null,
      "U_TX_Des_Mista": null,
      "U_TX_Des_ContaSuperior": null,
      "U_TX_NatAccount": null,
      "U_TX_NAT_REC": null,
      "U_TX_TipoReceitaBruta": null,
      "U_TX_RegCaixa": null,
      "U_TX_OcultarConta": null,
      "U_K_PlanoECDECF": null,
      "U_K33PCusType": "-"
    },
    {
      "Code": "1.1.07.02",
      "Name": "OUTROS CRÉDITOS",
      "Balance": 0.0,
      "CashAccount": "tNO",
      "BudgetAccount": "tNO",
      "ActiveAccount": "tNO",
      "PrimaryAccount": "tNO",
      "AccountLevel": 4,
      "DataExportCode": null,
      "FatherAccountKey": "1.1.07",
      "ExternalCode": "110702",
      "RateConversion": "tYES",
      "TaxLiableAccount": "tYES",
      "TaxExemptAccount": "tNO",
      "ExternalReconNo": null,
      "InternalReconNo": null,
      "AccountType": "at_Other",
      "AcctCurrency": "R$",
      "Balance_syscurr": 0.0,
      "Balance_FrgnCurr": 0.0,
      "Protected": "tNO",
      "ReconciledAccount": "tNO",
      "LiableForAdvances": "tNO",
      "ForeignName": null,
      "Details": null,
      "ProjectCode": null,
      "RevaluationCoordinated": "tNO",
      "LockManualTransaction": "tNO",
      "FormatCode": "1.1.07.02",
      "AllowChangeVatGroup": "tYES",
      "DefaultVatGroup": null,
      "Category": null,
      "TransactionCode": null,
      "LoadingType": "tNO",
      "LoadingFactorCode": null,
      "LoadingFactorCode2": null,
      "LoadingFactorCode3": null,
      "LoadingFactorCode4": null,
      "LoadingFactorCode5": null,
      "PlanningLevel": null,
      "DatevAccount": null,
      "DatevAutoAccount": "tNO",
      "DatevFirstDataEntry": "tYES",
      "AllowMultipleLinking": "tNO",
      "ProjectRelevant": "tNO",
      "DistributionRuleRelevant": "tNO",
      "DistributionRule2Relevant": "tNO",
      "DistributionRule3Relevant": "tNO",
      "DistributionRule4Relevant": "tNO",
      "DistributionRule5Relevant": "tNO",
      "BPLID": null,
      "BPLName": null,
      "VATRegNum": null,
      "AccountPurposeCode": null,
      "ReferentialAccountCode": null,
      "ValidFor": "tNO",
      "ValidFrom": null,
      "ValidTo": null,
      "ValidRemarks": null,
      "FrozenFor": "tNO",
      "FrozenFrom": null,
      "FrozenTo": null,
      "FrozenRemarks": null,
      "BlockManualPosting": "tYES",
      "CashFlowRelevant": "tNO",
      "PCN874ReportRelevant": "tNO",
      "PrimaryClosingAccount": null,
      "CostAccountingOnly": "tNO",
      "CostElementRelevant": "tNO",
      "CostElementCode": null,
      "StandardAccountCode": null,
      "TaxonomyCode": null,
      "IncomeClassificationCategory": null,
      "IncomeClassificationType": null,
      "ExpenseClassificationCategory": null,
      "ExpenseClassificationType": null,
      "U_TX_ContaCOSIF": null,
      "U_TX_CodigoDesIf": null,
      "U_TX_OutrosProdServDesIf": null,
      "U_TX_Des_Mista": null,
      "U_TX_Des_ContaSuperior": null,
      "U_TX_NatAccount": null,
      "U_TX_NAT_REC": null,
      "U_TX_TipoReceitaBruta": null,
      "U_TX_RegCaixa": null,
      "U_TX_OcultarConta": null,
      "U_K_PlanoECDECF": null,
      "U_K33PCusType": "-"
    },
    {
      "Code": "1.1.07.02.003",
      "Name": "Outros Valores a Receber",
      "Balance": 0.0,
      "CashAccount": "tNO",
      "BudgetAccount": "tNO",
      "ActiveAccount": "tYES",
      "PrimaryAccount": "tNO",
      "AccountLevel": 5,
      "DataExportCode": null,
      "FatherAccountKey": "1.1.07.02",
      "ExternalCode": "110702003",
      "RateConversion": "tYES",
      "TaxLiableAccount": "tYES",
      "TaxExemptAccount": "tNO",
      "ExternalReconNo": null,
      "InternalReconNo": null,
      "AccountType": "at_Other",
      "AcctCurrency": "R$",
      "Balance_syscurr": 0.0,
      "Balance_FrgnCurr": 0.0,
      "Protected": "tNO",
      "ReconciledAccount": "tNO",
      "LiableForAdvances": "tNO",
      "ForeignName": null,
      "Details": null,
      "ProjectCode": null,
      "RevaluationCoordinated": "tNO",
      "LockManualTransaction": "tNO",
      "FormatCode": "1.1.07.02.003",
      "AllowChangeVatGroup": "tYES",
      "DefaultVatGroup": null,
      "Category": null,
      "TransactionCode": null,
      "LoadingType": "tNO",
      "LoadingFactorCode": null,
      "LoadingFactorCode2": null,
      "LoadingFactorCode3": null,
      "LoadingFactorCode4": null,
      "LoadingFactorCode5": null,
      "PlanningLevel": null,
      "DatevAccount": null,
      "DatevAutoAccount": "tNO",
      "DatevFirstDataEntry": "tYES",
      "AllowMultipleLinking": "tNO",
      "ProjectRelevant": "tNO",
      "DistributionRuleRelevant": "tNO",
      "DistributionRule2Relevant": "tNO",
      "DistributionRule3Relevant": "tNO",
      "DistributionRule4Relevant": "tNO",
      "DistributionRule5Relevant": "tNO",
      "BPLID": null,
      "BPLName": null,
      "VATRegNum": null,
      "AccountPurposeCode": null,
      "ReferentialAccountCode": null,
      "ValidFor": "tNO",
      "ValidFrom": null,
      "ValidTo": null,
      "ValidRemarks": null,
      "FrozenFor": "tNO",
      "FrozenFrom": null,
      "FrozenTo": null,
      "FrozenRemarks": null,
      "BlockManualPosting": "tNO",
      "CashFlowRelevant": "tNO",
      "PCN874ReportRelevant": "tNO",
      "PrimaryClosingAccount": null,
      "CostAccountingOnly": "tNO",
      "CostElementRelevant": "tNO",
      "CostElementCode": null,
      "StandardAccountCode": null,
      "TaxonomyCode": null,
      "IncomeClassificationCategory": null,
      "IncomeClassificationType": null,
      "ExpenseClassificationCategory": null,
      "ExpenseClassificationType": null,
      "U_TX_ContaCOSIF": null,
      "U_TX_CodigoDesIf": null,
      "U_TX_OutrosProdServDesIf": null,
      "U_TX_Des_Mista": null,
      "U_TX_Des_ContaSuperior": null,
      "U_TX_NatAccount": null,
      "U_TX_NAT_REC": null,
      "U_TX_TipoReceitaBruta": null,
      "U_TX_RegCaixa": null,
      "U_TX_OcultarConta": null,
      "U_K_PlanoECDECF": null,
      "U_K33PCusType": "-"
    }
  ]
}